[
  {
    "id": "test-slide-1",
    "elements": [
      {
        "type": "shape",
        "id": "4cbRxp",
        "left": 0,
        "top": 200,
        "width": 546,
        "height": 362.5,
        "viewBox": [
          200,
          200
        ],
        "path": "M 0 0 L 0 200 L 200 200 Z",
        "fill": "#5b9bd5",
        "fixedRatio": false,
        "opacity": 0.7,
        "rotate": 0
      },
      {
        "type": "shape",
        "id": "ookHrf",
        "left": 0,
        "top": 0,
        "width": 300,
        "height": 320,
        "viewBox": [
          200,
          200
        ],
        "path": "M 0 0 L 0 200 L 200 200 Z",
        "fill": "#5b9bd5",
        "fixedRatio": false,
        "flipV": true,
        "rotate": 0
      },
      {
        "type": "text",
        "id": "idn7Mx",
        "left": 355,
        "top": 65.25,
        "width": 585,
        "height": 154.390625,
        "lineHeight": 1.2,
        "content": "<p><strong><span style='font-size:  112px'>BKT JSC</span></strong></p>",
        "rotate": 0,
        "defaultFontName": "Arial",
        "defaultColor": "#333"
      },
      {
        "type": "text",
        "id": "7stmVP",
        "left": 355,
        "top": 253.25,
        "width": 585,
        "height": 56,
        "content": "<p><span style='font-size:  24px'>Ứng dụng soạn giảng trực tuyến</span></p>",
        "rotate": 0,
        "defaultFontName": "Arial",
        "defaultColor": "#333"
      },
      {
        "type": "line",
        "id": "FnpZs4",
        "left": 361,
        "top": 238,
        "start": [
          0,
          0
        ],
        "end": [
          549,
          0
        ],
        "points": [
          "",
          ""
        ],
        "color": "#5b9bd5",
        "style": "solid",
        "width": 2
      },
      {
        "type": "exercise",
        "id": "9r4EFMWZdz",
        "excerciseType": "single",
        "borderRadius": 10,
        "isBorder": true,
        "isPreview": false,
        "fill": "rgb(240, 248, 255)",
        "gradient": {
          "type": "linear",
          "rotate": 0,
          "color": [
            "#fff",
            "rgb(240, 248, 255)"
          ]
        },
        "fillType": "fill",
        "left": 245.99999999999997,
        "top": 49.99999999999999,
        "fontName": "Arial",
        "answerBackground": "rgb(240, 248, 255)",
        "color": "#000",
        "btnColor": "#337ab7",
        "btnTextColor": "white",
        "width": 618.2038834951456,
        "height": 396.07605177993526,
        "rotate": 0,
        "fontSize": "24px",
        "data": [
          {
            "AnswerString": "A",
            "backgroundColor": "transparent",
            "IsChecked": false,
            "IsImageUrl": false,
            "ID": "fNcAeJNHQD"
          },
          {
            "AnswerString": "B",
            "backgroundColor": "transparent",
            "IsChecked": false,
            "IsImageUrl": false,
            "ID": "34XqYaoxb3"
          },
          {
            "AnswerString": "C",
            "backgroundColor": "transparent",
            "IsChecked": false,
            "IsImageUrl": false,
            "ID": "BqJHKwuRzY"
          },
          {
            "AnswerString": "D",
            "backgroundColor": "transparent",
            "IsChecked": false,
            "IsImageUrl": false,
            "ID": "WRNJcDHbD8"
          },
          {
            "AnswerString": "Câu hỏi mới",
            "backgroundColor": "transparent",
            "IsChecked": false,
            "IsImageUrl": false,
            "ID": "Iw45AFGUUG"
          }
        ],
        "dataPreview": [
          {
            "AnswerString": "A",
            "backgroundColor": "rgb(240, 248, 255)",
            "IsChecked": false,
            "IsImageUrl": false,
            "ID": "fNcAeJNHQD"
          },
          {
            "AnswerString": "B",
            "backgroundColor": "rgb(240, 248, 255)",
            "IsChecked": false,
            "IsImageUrl": false,
            "ID": "34XqYaoxb3"
          },
          {
            "AnswerString": "C",
            "backgroundColor": "rgb(240, 248, 255)",
            "IsChecked": false,
            "IsImageUrl": false,
            "ID": "BqJHKwuRzY"
          },
          {
            "AnswerString": "D",
            "backgroundColor": "rgb(240, 248, 255)",
            "IsChecked": false,
            "IsImageUrl": false,
            "ID": "WRNJcDHbD8"
          },
          {
            "AnswerString": "Câu hỏi mới",
            "backgroundColor": "rgb(240, 248, 255)",
            "IsChecked": false,
            "IsImageUrl": false,
            "ID": "Iw45AFGUUG"
          }
        ]
      },
      {
        "type": "shape",
        "id": "ZEbM-oLpjc",
        "left": 24.676369231881452,
        "top": 178.98462783171522,
        "width": 202.26537216828476,
        "height": 202.26537216828476,
        "viewBox": [
          1024,
          1024
        ],
        "path": "M927.78951111 340.39277037c-12.01493333-47.81700741 12.01493333-124.03294815 89.08041481-150.97552592l-82.40545184-4.36906667s-31.19028148-109.22666667-174.27721483-118.9357037c-143.08693333-9.8304-236.65777778-3.64088889-236.65777777-3.6408889s106.07122963 67.47780741 63.5941926 187.74850371c-31.06891852 63.71555555-79.85682963 116.02299259-132.04290371 175.61220741-1.57771852 1.57771852-3.03407408 3.15543703-4.2477037 4.49042962C278.25493333 624.86755555 7.13007408 934.34311111 7.13007408 934.34311111c298.43152592 78.15774815 498.43768889-7.64586667 616.76657777-110.56165926 24.87940741-0.24272592 43.5693037-0.36408889 56.19105185-0.36408888 164.8109037 0 304.13558518-142.72284445 298.43152593-301.4656-3.88361482-109.1053037-38.71478518-133.74198518-50.72971852-181.5589926z",
        "fill": "#5b9bd5",
        "fixedRatio": false,
        "rotate": 68.04160387948993,
        "special": true,
        "gradient": {
          "type": "radial",
          "rotate": 0,
          "color": [
            "rgba(136,31,31,1)",
            "rgba(89,89,89,1)"
          ]
        },
        "flipH": false,
        "flipV": true
      }
    ],
    "background": {
      "type": "solid",
      "color": "#ffffff"
    }
  },
  {
    "id": "test-slide-2",
    "elements": [
      {
        "type": "text",
        "id": "ptNnUJ",
        "left": 145,
        "top": 148,
        "width": 711,
        "height": 77.59375,
        "lineHeight": 1.2,
        "content": "<p style='text-align: center;'><strong><span style='font-size: 48px'>Thêm tiêu đề ở đây</span></strong></p>",
        "rotate": 0,
        "defaultFontName": "Arial",
        "defaultColor": "#333"
      },
      {
        "type": "text",
        "id": "mRHvQN",
        "left": 207.50000000000003,
        "top": 249.84259259259264,
        "width": 585,
        "height": 56,
        "content": "<p style='text-align: center;'><span style='font-size: 24px'>Thêm tiêu đề ở đây</span></p>",
        "rotate": 0,
        "defaultFontName": "Arial",
        "defaultColor": "#333"
      },
      {
        "type": "line",
        "id": "7CQDwc",
        "left": 323.09259259259267,
        "top": 238.33333333333334,
        "start": [
          0,
          0
        ],
        "end": [
          354.8148148148148,
          0
        ],
        "points": [
          "",
          ""
        ],
        "color": "#5b9bd5",
        "style": "solid",
        "width": 4
      },
      {
        "type": "shape",
        "id": "09wqWw",
        "left": -27.648148148148138,
        "top": 432.73148148148147,
        "width": 1056.2962962962963,
        "height": 162.96296296296296,
        "viewBox": [
          200,
          200
        ],
        "path": "M 0 20 C 40 -40 60 60 100 20 C 140 -40 160 60 200 20 L 200 180 C 140 240 160 140 100 180 C 40 240 60 140 0 180 L 0 20 Z",
        "fill": "#5b9bd5",
        "fixedRatio": false,
        "rotate": 0
      }
    ],
    "background": {
      "type": "solid",
      "color": "#fff"
    }
  },
  {
    "id": "test-slide-3",
    "elements": [
      {
        "type": "shape",
        "id": "vSheCJ",
        "left": 183.5185185185185,
        "top": 175.5092592592593,
        "width": 605.1851851851851,
        "height": 185.18518518518516,
        "viewBox": [
          200,
          200
        ],
        "path": "M 0 0 L 200 0 L 200 200 L 0 200 Z",
        "fill": "#5b9bd5",
        "fixedRatio": false,
        "rotate": 0
      },
      {
        "type": "shape",
        "id": "Mpwv7x",
        "left": 211.29629629629628,
        "top": 201.80555555555557,
        "width": 605.1851851851851,
        "height": 185.18518518518516,
        "viewBox": [
          200,
          200
        ],
        "path": "M 0 0 L 200 0 L 200 200 L 0 200 Z",
        "fill": "#5b9bd5",
        "fixedRatio": false,
        "rotate": 0,
        "opacity": 0.7
      },
      {
        "type": "text",
        "id": "WQOTAp",
        "left": 300.9074074074074,
        "top": 188.10185185185182,
        "width": 417.9629629629629,
        "height": 140,
        "content": "<p style='text-align: center;'><strong><span style='font-size: 54px'>Cảm ơn</span></></strong></p>",
        "rotate": 0,
        "defaultFontName": "Arial",
        "defaultColor": "#333",
        "wordSpace": 5
      }
    ],
    "background": {
      "type": "solid",
      "color": "#fff"
    }
  }
]